apple_vision_utils/__init__.py
apple_vision_utils/cli.py
apple_vision_utils/utils.py
apple_vision_utils-1.0.2.dist-info/LICENSE
apple_vision_utils-1.0.2.dist-info/METADATA
apple_vision_utils-1.0.2.dist-info/WHEEL
apple_vision_utils-1.0.2.dist-info/entry_points.txt
apple_vision_utils-1.0.2.dist-info/RECORD
